{"dependencies":[{"name":"/Users/seanjeluo/Code/setsun.github.io/package.json","includedInParent":true,"mtime":1523668200854},{"name":"/Users/seanjeluo/Code/setsun.github.io/.babelrc","includedInParent":true,"mtime":1522638942309},{"name":"/Users/seanjeluo/Code/setsun.github.io/node_modules/rebass/package.json","includedInParent":true,"mtime":1523475461005},{"name":"/Users/seanjeluo/Code/setsun.github.io/node_modules/rebass/.babelrc","includedInParent":true,"mtime":1519080670000},{"name":"styled-components","loc":{"line":8,"column":32}},{"name":"./Text","loc":{"line":12,"column":20}},{"name":"styled-system","loc":{"line":16,"column":28}}],"generated":{"js":"'use strict';\n\nObject.defineProperty(exports, \"__esModule\", {\n  value: true\n});\nexports.Caps = undefined;\n\nvar _styledComponents = require('styled-components');\n\nvar _styledComponents2 = _interopRequireDefault(_styledComponents);\n\nvar _Text = require('./Text');\n\nvar _Text2 = _interopRequireDefault(_Text);\n\nvar _styledSystem = require('styled-system');\n\nfunction _interopRequireDefault(obj) { return obj && obj.__esModule ? obj : { default: obj }; }\n\nvar Caps = exports.Caps = (0, _styledComponents2.default)(_Text2.default)([], _styledSystem.letterSpacing, {\n  textTransform: 'uppercase'\n});\n\nCaps.displayName = 'Caps';\n\nCaps.defaultProps = {\n  fontSize: 0,\n  letterSpacing: '0.2em'\n};\n\nexports.default = Caps;","map":{"mappings":[{"source":"../node_modules/rebass/dist/Caps.js","original":{"line":1,"column":0},"generated":{"line":1,"column":0}},{"source":"../node_modules/rebass/dist/Caps.js","original":{"line":2,"column":0},"generated":{"line":2,"column":0}},{"source":"../node_modules/rebass/dist/Caps.js","original":{"line":3,"column":0},"generated":{"line":3,"column":0}},{"source":"../node_modules/rebass/dist/Caps.js","original":{"line":4,"column":0},"generated":{"line":4,"column":0}},{"source":"../node_modules/rebass/dist/Caps.js","original":{"line":5,"column":0},"generated":{"line":5,"column":0}},{"source":"../node_modules/rebass/dist/Caps.js","original":{"line":6,"column":0},"generated":{"line":6,"column":0}},{"source":"../node_modules/rebass/dist/Caps.js","original":{"line":7,"column":0},"generated":{"line":7,"column":0}},{"source":"../node_modules/rebass/dist/Caps.js","original":{"line":8,"column":0},"generated":{"line":8,"column":0}},{"source":"../node_modules/rebass/dist/Caps.js","original":{"line":9,"column":0},"generated":{"line":9,"column":0}},{"source":"../node_modules/rebass/dist/Caps.js","original":{"line":10,"column":0},"generated":{"line":10,"column":0}},{"source":"../node_modules/rebass/dist/Caps.js","original":{"line":11,"column":0},"generated":{"line":11,"column":0}},{"source":"../node_modules/rebass/dist/Caps.js","original":{"line":12,"column":0},"generated":{"line":12,"column":0}},{"source":"../node_modules/rebass/dist/Caps.js","original":{"line":13,"column":0},"generated":{"line":13,"column":0}},{"source":"../node_modules/rebass/dist/Caps.js","original":{"line":14,"column":0},"generated":{"line":14,"column":0}},{"source":"../node_modules/rebass/dist/Caps.js","original":{"line":15,"column":0},"generated":{"line":15,"column":0}},{"source":"../node_modules/rebass/dist/Caps.js","original":{"line":16,"column":0},"generated":{"line":16,"column":0}},{"source":"../node_modules/rebass/dist/Caps.js","original":{"line":17,"column":0},"generated":{"line":17,"column":0}},{"source":"../node_modules/rebass/dist/Caps.js","original":{"line":18,"column":0},"generated":{"line":18,"column":0}},{"source":"../node_modules/rebass/dist/Caps.js","original":{"line":19,"column":0},"generated":{"line":19,"column":0}},{"source":"../node_modules/rebass/dist/Caps.js","original":{"line":20,"column":0},"generated":{"line":20,"column":0}},{"source":"../node_modules/rebass/dist/Caps.js","original":{"line":21,"column":0},"generated":{"line":21,"column":0}},{"source":"../node_modules/rebass/dist/Caps.js","original":{"line":22,"column":0},"generated":{"line":22,"column":0}},{"source":"../node_modules/rebass/dist/Caps.js","original":{"line":23,"column":0},"generated":{"line":23,"column":0}},{"source":"../node_modules/rebass/dist/Caps.js","original":{"line":24,"column":0},"generated":{"line":24,"column":0}},{"source":"../node_modules/rebass/dist/Caps.js","original":{"line":25,"column":0},"generated":{"line":25,"column":0}},{"source":"../node_modules/rebass/dist/Caps.js","original":{"line":26,"column":0},"generated":{"line":26,"column":0}},{"source":"../node_modules/rebass/dist/Caps.js","original":{"line":27,"column":0},"generated":{"line":27,"column":0}},{"source":"../node_modules/rebass/dist/Caps.js","original":{"line":28,"column":0},"generated":{"line":28,"column":0}},{"source":"../node_modules/rebass/dist/Caps.js","original":{"line":29,"column":0},"generated":{"line":29,"column":0}},{"source":"../node_modules/rebass/dist/Caps.js","original":{"line":30,"column":0},"generated":{"line":30,"column":0}},{"source":"../node_modules/rebass/dist/Caps.js","original":{"line":31,"column":0},"generated":{"line":31,"column":0}}],"sources":{"../node_modules/rebass/dist/Caps.js":"'use strict';\n\nObject.defineProperty(exports, \"__esModule\", {\n  value: true\n});\nexports.Caps = undefined;\n\nvar _styledComponents = require('styled-components');\n\nvar _styledComponents2 = _interopRequireDefault(_styledComponents);\n\nvar _Text = require('./Text');\n\nvar _Text2 = _interopRequireDefault(_Text);\n\nvar _styledSystem = require('styled-system');\n\nfunction _interopRequireDefault(obj) { return obj && obj.__esModule ? obj : { default: obj }; }\n\nvar Caps = exports.Caps = (0, _styledComponents2.default)(_Text2.default)([], _styledSystem.letterSpacing, {\n  textTransform: 'uppercase'\n});\n\nCaps.displayName = 'Caps';\n\nCaps.defaultProps = {\n  fontSize: 0,\n  letterSpacing: '0.2em'\n};\n\nexports.default = Caps;"},"lineCount":31}},"hash":"9cd4fe08a26ce3550c9d31bcdea0ec37","cacheData":{"env":{}}}