{
  "dependencies": [
    { "name": "./_a-function", "loc": { "line": 1, "column": 24 } },
    { "name": "./_to-object", "loc": { "line": 2, "column": 23 } },
    { "name": "./_iobject", "loc": { "line": 3, "column": 22 } },
    { "name": "./_to-length", "loc": { "line": 4, "column": 23 } }
  ],
  "generated": {
    "js":
      "var r=require(\"./_a-function\"),e=require(\"./_to-object\"),i=require(\"./_iobject\"),o=require(\"./_to-length\");module.exports=function(t,n,u,a,f){r(n);var c=e(t),l=i(c),h=o(c.length),q=f?h-1:0,_=f?-1:1;if(u<2)for(;;){if(q in l){a=l[q],q+=_;break}if(q+=_,f?q<0:h<=q)throw TypeError(\"Reduce of empty array with no initial value\")}for(;f?q>=0:h>q;q+=_)q in l&&(a=n(a,l[q],q,c));return a};"
  },
  "hash": "e899ca801b1cffe8f5c182e209023be8"
}
